ziku
