Metadata-Version: 2.1
Name: ziku
Version: 0.1.3
Summary: 一个往图片上写汉字的软件包
Home-page: https://github.com/pypa/sampleproject
Author: 赵明明
Author-email: 13271929138@163.com
Project-URL: Bug Tracker, https://github.com/pypa/sampleproject/issues
Classifier: Programming Language :: Python :: 3
Classifier: License :: OSI Approved :: MIT License
Classifier: Operating System :: OS Independent
Requires-Python: >=3.6
